Metadata-Version: 2.2
Name: django-tapeforms
Version: 2.3.0
Summary: A helper to render Django forms using HTML templates.
Author-email: Stephan Jaekel <steph@rdev.info>
Project-URL: Homepage, https://github.com/stephrdev/django-tapeforms
Project-URL: Repository, https://github.com/stephrdev/django-tapeforms
Project-URL: Documentation, https://django-tapeforms.readthedocs.io
Classifier: Development Status :: 5 - Production/Stable
Classifier: License :: OSI Approved :: MIT License
Classifier: Environment :: Web Environment
Classifier: Framework :: Django
Classifier: Intended Audience :: Developers
Classifier: Operating System :: Unix
Classifier: Programming Language :: Python
Classifier: Programming Language :: Python :: 3
Requires-Python: <4,>=3.8
Requires-Dist: Django>=4.2
